embeddoor/__init__.py
embeddoor/app.py
embeddoor/cli.py
embeddoor/data_manager.py
embeddoor/dimred.py
embeddoor/routes.py
embeddoor/visualization.py
embeddoor/dim_red/__init__.py
embeddoor/dim_red/base.py
embeddoor/dim_red/pca.py
embeddoor/dim_red/tsne.py
embeddoor/dim_red/umap.py
embeddoor/embeddings/__init__.py
embeddoor/embeddings/base.py
embeddoor/embeddings/providers/__init__.py
embeddoor/embeddings/providers/clip_provider.py
embeddoor/embeddings/providers/gemini.py
embeddoor/embeddings/providers/huggingface.py
embeddoor/embeddings/providers/openai_provider.py
embeddoor/static/css/style.css
embeddoor/static/js/app.js
embeddoor/templates/index.html
embeddoor/views/__init__.py
embeddoor/views/correlation.py
embeddoor/views/heatmap.py
embeddoor/views/images.py
embeddoor/views/plot.py
embeddoor/views/ridgeplot.py
embeddoor/views/table.py
embeddoor/views/terminal.py
embeddoor/views/wordcloud.py
embeddoor-0.1.0.dist-info/licenses/LICENSE
embeddoor-0.1.0.dist-info/METADATA
embeddoor-0.1.0.dist-info/WHEEL
embeddoor-0.1.0.dist-info/entry_points.txt
embeddoor-0.1.0.dist-info/top_level.txt
embeddoor-0.1.0.dist-info/RECORD
