Metadata-Version: 2.4
Name: embeddoor
Version: 0.1.0
Summary: A browser-based embedding visualization and analysis tool
Author-email: Robert Haase <robert.haase@uni-leipzig.de>
License: License :: OSI Approved :: MIT License
Keywords: embeddings,visualization,dimensionality-reduction,data-analysis
Classifier: Development Status :: 3 - Alpha
Classifier: Intended Audience :: Science/Research
Classifier: License :: OSI Approved :: MIT License
Classifier: Operating System :: OS Independent
Classifier: Programming Language :: Python :: 3
Classifier: Programming Language :: Python :: 3.8
Classifier: Programming Language :: Python :: 3.9
Classifier: Programming Language :: Python :: 3.10
Classifier: Programming Language :: Python :: 3.11
Requires-Python: >=3.8
License-File: LICENSE
Requires-Dist: flask>=2.3.0
Requires-Dist: pandas>=2.0.0
Requires-Dist: numpy>=1.24.0
Requires-Dist: plotly>=5.14.0
Requires-Dist: scikit-learn>=1.3.0
Requires-Dist: pyarrow>=12.0.0
Requires-Dist: umap-learn>=0.5.3
Requires-Dist: pillow>=9.5.0
Requires-Dist: wordcloud>=1.9.0
Provides-Extra: dev
Requires-Dist: pytest>=7.3.0; extra == "dev"
Requires-Dist: pytest-cov>=4.1.0; extra == "dev"
Requires-Dist: black>=23.3.0; extra == "dev"
Requires-Dist: flake8>=6.0.0; extra == "dev"
Provides-Extra: embeddings
Requires-Dist: transformers>=4.30.0; extra == "embeddings"
Requires-Dist: torch>=2.0.0; extra == "embeddings"
Requires-Dist: sentence-transformers>=2.2.2; extra == "embeddings"
Requires-Dist: openai>=1.0.0; extra == "embeddings"
Requires-Dist: google-generativeai>=0.3.0; extra == "embeddings"
Dynamic: license-file
